qpyson/__init__.py
qpyson/cli.py
qpyson-0.3.0.dist-info/LICENSE
qpyson-0.3.0.dist-info/METADATA
qpyson-0.3.0.dist-info/WHEEL
qpyson-0.3.0.dist-info/entry_points.txt
qpyson-0.3.0.dist-info/top_level.txt
qpyson-0.3.0.dist-info/RECORD
