Metadata-Version: 2.1
Name: qpyson
Version: 0.3.0
Summary: JQ-ish tool to query/munge JSON files using Python
Home-page: http://github.com/mpkocher/qpyson
Author: M. Kocher
Author-email: michael.kocher@me.com
License: MIT
Platform: UNKNOWN
Classifier: Programming Language :: Python :: 3
Classifier: License :: OSI Approved :: MIT License
Classifier: Operating System :: OS Independent
Requires-Python: >=3.6
Requires-Dist: tabulate
